odoo/addons/sale_invoice_frequency/README.rst
odoo/addons/sale_invoice_frequency/__init__.py
odoo/addons/sale_invoice_frequency/__manifest__.py
odoo/addons/sale_invoice_frequency/data/sale_invoice_frequency_data.xml
odoo/addons/sale_invoice_frequency/i18n/de.po
odoo/addons/sale_invoice_frequency/i18n/es.po
odoo/addons/sale_invoice_frequency/i18n/fr.po
odoo/addons/sale_invoice_frequency/i18n/it.po
odoo/addons/sale_invoice_frequency/i18n/sale_invoice_frequency.pot
odoo/addons/sale_invoice_frequency/models/__init__.py
odoo/addons/sale_invoice_frequency/models/res_partner.py
odoo/addons/sale_invoice_frequency/models/sale_invoice_frequency.py
odoo/addons/sale_invoice_frequency/models/sale_order.py
odoo/addons/sale_invoice_frequency/readme/CONTRIBUTORS.md
odoo/addons/sale_invoice_frequency/readme/DESCRIPTION.md
odoo/addons/sale_invoice_frequency/readme/ROADMAP.md
odoo/addons/sale_invoice_frequency/readme/USAGE.md
odoo/addons/sale_invoice_frequency/security/ir.model.access.csv
odoo/addons/sale_invoice_frequency/static/description/icon.png
odoo/addons/sale_invoice_frequency/static/description/index.html
odoo/addons/sale_invoice_frequency/views/res_partner_view.xml
odoo/addons/sale_invoice_frequency/views/sale_invoice_frequency_view.xml
odoo/addons/sale_invoice_frequency/views/sale_order_view.xml
odoo_addon_sale_invoice_frequency-18.0.1.0.1.dist-info/METADATA
odoo_addon_sale_invoice_frequency-18.0.1.0.1.dist-info/WHEEL
odoo_addon_sale_invoice_frequency-18.0.1.0.1.dist-info/top_level.txt
odoo_addon_sale_invoice_frequency-18.0.1.0.1.dist-info/RECORD
